legion_query_runner/__init__.py
legion_query_runner/query_runner/__init__.py
legion_query_runner/query_runner/base.py
legion_query_runner/query_runner/big_query.py
legion_query_runner/query_runner/mssql.py
legion_query_runner/query_runner/mysql.py
legion_query_runner/query_runner/oracle.py
legion_query_runner/query_runner/pg.py
legion_query_runner/query_runner/sqlite.py
legion_query_runner/query_runner/utils/__init__.py
legion_query_runner/query_runner/utils/json_utils.py
legion_query_runner/query_runner/utils/requests_session.py
legion_query_runner/query_runner/utils.py
legion_query_runner/settings/__init__.py
legion_query_runner/settings/dynamic_settings.py
legion_query_runner/settings/helpers.py
legion_query_runner/util/settings.py
legion_query_runner/util/utils.py
legion_query_runner-0.1.4.dist-info/LICENSE
legion_query_runner-0.1.4.dist-info/METADATA
legion_query_runner-0.1.4.dist-info/WHEEL
legion_query_runner-0.1.4.dist-info/RECORD
